langtrain/__init__.py
langtrain/utils.py
langtrain/config/__init__.py
langtrain/config/config.py
langtrain/data/__init__.py
langtrain/data/base.py
langtrain/data/causal.py
langtrain/data/dataloader.py
langtrain/data/masked.py
langtrain/data/vision.py
langtrain/model/__init__.py
langtrain/model/bert.py
langtrain/model/gpt.py
langtrain/model/llama.py
langtrain/model/modeling_utils.py
langtrain/model/vit.py
langtrain/nn/__init__.py
langtrain/nn/nn.py
langtrain/tokenizer/__init__.py
langtrain/tokenizer/base.py
langtrain/tokenizer/sentencepiece.py
langtrain/trainer/__init__.py
langtrain/trainer/trainer.py
langtrain/trainer/trainer_utils.py
langtrain-0.0.4.dist-info/licenses/LICENSE
langtrain-0.0.4.dist-info/METADATA
langtrain-0.0.4.dist-info/WHEEL
langtrain-0.0.4.dist-info/top_level.txt
langtrain-0.0.4.dist-info/RECORD
