Metadata-Version: 2.4
Name: langtrain
Version: 0.0.4
Summary: Language Model Training Library
Author-email: Sayed Shaun <sayedshaun4@gmail.com>
Keywords: nlp,cv,language model,model training,langtrain
Classifier: Programming Language :: Python :: 3
Classifier: License :: OSI Approved :: MIT License
Classifier: Operating System :: OS Independent
Requires-Python: >=3.10
License-File: LICENSE
Requires-Dist: numpy==2.2.5
Requires-Dist: Pillow==11.2.1
Requires-Dist: platformdirs==4.3.7
Requires-Dist: pytest==8.3.5
Requires-Dist: PyYAML==6.0.2
Requires-Dist: sentencepiece==0.2.0
Requires-Dist: tomli==2.2.1
Requires-Dist: tqdm==4.67.1
Requires-Dist: wandb==0.19.10
Dynamic: license-file
